LICENSE
gbbox/__init__.py
gbbox/constants.py
gbbox/objects.py
gbbox-0.1.1.dist-info/LICENSE
gbbox-0.1.1.dist-info/WHEEL
gbbox-0.1.1.dist-info/METADATA
gbbox-0.1.1.dist-info/RECORD
