Metadata-Version: 2.1
Name: gbbox
Version: 0.1.1
Summary: Simple Python module for calculating bounding box (bbox) from given GeoJSON object
Home-page: https://github.com/luqqk/geojson-bbox
License: MIT
Keywords: python,gis,geojson,bbox
Author: Łukasz Mikołajczak
Author-email: mikolajczak.luq@gmail.com
Requires-Python: >=3.9.5,<4.0.0
Classifier: Development Status :: 4 - Beta
Classifier: Intended Audience :: Developers
Classifier: Intended Audience :: Science/Research
Classifier: License :: OSI Approved :: MIT License
Classifier: Programming Language :: Python :: 3
Classifier: Programming Language :: Python :: 3.10
Classifier: Programming Language :: Python :: 3.9
Classifier: Topic :: Scientific/Engineering :: GIS
Classifier: Topic :: Software Development :: Libraries :: Python Modules
Requires-Dist: pydantic (==1.9.1)
Project-URL: Repository, https://github.com/luqqk/geojson-bbox
